stripe-stubs/METADATA.toml
stripe-stubs/__init__.pyi
stripe-stubs/api_requestor.pyi
stripe-stubs/error.pyi
stripe-stubs/http_client.pyi
stripe-stubs/multipart_data_generator.pyi
stripe-stubs/oauth.pyi
stripe-stubs/oauth_error.pyi
stripe-stubs/object_classes.pyi
stripe-stubs/py.typed
stripe-stubs/request_metrics.pyi
stripe-stubs/stripe_object.pyi
stripe-stubs/stripe_response.pyi
stripe-stubs/util.pyi
stripe-stubs/version.pyi
stripe-stubs/webhook.pyi
stripe-stubs/api_resources/__init__.pyi
stripe-stubs/api_resources/account.pyi
stripe-stubs/api_resources/account_link.pyi
stripe-stubs/api_resources/alipay_account.pyi
stripe-stubs/api_resources/apple_pay_domain.pyi
stripe-stubs/api_resources/application_fee.pyi
stripe-stubs/api_resources/application_fee_refund.pyi
stripe-stubs/api_resources/balance.pyi
stripe-stubs/api_resources/balance_transaction.pyi
stripe-stubs/api_resources/bank_account.pyi
stripe-stubs/api_resources/bitcoin_receiver.pyi
stripe-stubs/api_resources/bitcoin_transaction.pyi
stripe-stubs/api_resources/capability.pyi
stripe-stubs/api_resources/card.pyi
stripe-stubs/api_resources/charge.pyi
stripe-stubs/api_resources/country_spec.pyi
stripe-stubs/api_resources/coupon.pyi
stripe-stubs/api_resources/credit_note.pyi
stripe-stubs/api_resources/credit_note_line_item.pyi
stripe-stubs/api_resources/customer.pyi
stripe-stubs/api_resources/customer_balance_transaction.pyi
stripe-stubs/api_resources/dispute.pyi
stripe-stubs/api_resources/ephemeral_key.pyi
stripe-stubs/api_resources/error_object.pyi
stripe-stubs/api_resources/event.pyi
stripe-stubs/api_resources/exchange_rate.pyi
stripe-stubs/api_resources/file.pyi
stripe-stubs/api_resources/file_link.pyi
stripe-stubs/api_resources/invoice.pyi
stripe-stubs/api_resources/invoice_item.pyi
stripe-stubs/api_resources/invoice_line_item.pyi
stripe-stubs/api_resources/issuer_fraud_record.pyi
stripe-stubs/api_resources/line_item.pyi
stripe-stubs/api_resources/list_object.pyi
stripe-stubs/api_resources/login_link.pyi
types_stripe-3.5.2.15.dist-info/METADATA
types_stripe-3.5.2.15.dist-info/WHEEL
types_stripe-3.5.2.15.dist-info/top_level.txt
types_stripe-3.5.2.15.dist-info/RECORD
